[["273105045",{"id":"273105045","location":"127735269","language":"ru","save_par":{},"_type":"player","genus":"human","status":{"send":true,"view":true},"parameters":{"health":99.44125683632093,"maxHealth":99.44124689219623,"regeneration":9.999999994426162,"regenerationTime":1,"regenerationInterval":10.000000005573838,"damage":19.037214299774867,"attackTime":0,"attackInterval":5.253683696797161,"inaccuracyDamage":40},"player":true,"online":true}],["373112782",{"id":"373112782","location":"127735269","language":"ru","save_par":{"entity":{"health":-67,"maxHealth":0,"regeneration":0,"damage":0,"inaccuracyDamage":0}},"_type":"corpse","genus":"human","status":{"send":false,"view":true},"parameters":{"health":0,"maxHealth":0,"regeneration":0,"damage":0,"inaccuracyDamage":0}}]]